README.md
setup.py
nmeaanalyzer/__init__.py
nmeaanalyzer/_version.py
nmeaanalyzer/parse.py
nmeaanalyzer/plot.py
nmeaanalyzer.egg-info/PKG-INFO
nmeaanalyzer.egg-info/SOURCES.txt
nmeaanalyzer.egg-info/dependency_links.txt
nmeaanalyzer.egg-info/entry_points.txt
nmeaanalyzer.egg-info/requires.txt
nmeaanalyzer.egg-info/top_level.txt