Metadata-Version: 1.1
Name: nmeaanalyzer
Version: 0.0.4
Summary: Python library for the NMEA 0183 analyzer
Home-page: https://github.com/embest/nmeaanalyzer
Author: Wayne Guo
Author-email: wayne.guo@embest.net
License: Apache License 2.0
Keywords: python nmea gps analyzer nmea0183 0183
Platform: UNKNOWN
Classifier: Intended Audience :: Developers
Classifier: Operating System :: OS Independent
Classifier: Programming Language :: Python :: 3
Classifier: Programming Language :: Python :: 3.3
Classifier: Programming Language :: Python :: 3.4
Classifier: Programming Language :: Python :: 3.5
Classifier: Programming Language :: Python :: Implementation :: PyPy
Classifier: Topic :: Scientific/Engineering :: GIS
Classifier: Topic :: Software Development :: Libraries :: Python Modules
